autoprop/__init__.py
autoprop/cache.py
autoprop/decorators.py
autoprop/policies.py
autoprop-4.0.2.dist-info/LICENSE.txt
autoprop-4.0.2.dist-info/WHEEL
autoprop-4.0.2.dist-info/METADATA
autoprop-4.0.2.dist-info/RECORD
