Metadata-Version: 2.1
Name: autoprop
Version: 4.0.2
Summary: Infer properties from accessor methods.
Home-page: https://github.com/kalekundert/autoprop
Author: Kale Kundert
Author-email: kale@thekunderts.net
Requires-Python: ~=3.6
Classifier: Programming Language :: Python :: 3
Classifier: License :: OSI Approved :: MIT License
Requires-Dist: signature_dispatch~=1.0
Requires-Dist: backports.cached-property;python_version<"3.8"
Requires-Dist: sphinx ; extra == "doc"
Requires-Dist: sphinx_rtd_theme ; extra == "doc"
Requires-Dist: autoclasstoc ; extra == "doc"
Requires-Dist: pytest ; extra == "test"
Requires-Dist: pytest-cov ; extra == "test"
Requires-Dist: coveralls ; extra == "test"
Project-URL: Bug Tracker, https://github.com/kalekundert/autoprop/issues
Project-URL: Continuous Integration, https://github.com/kalekundert/autoprop/actions
Project-URL: Documentation, https://autoprop.readthedocs.io/en/latest/
Project-URL: Test Coverage, https://coveralls.io/github/kalekundert/autoprop
Project-URL: Version Control, https://github.com/kalekundert/autoprop
Provides-Extra: doc
Provides-Extra: test
